transiflow/BoundaryConditions.py
transiflow/Continuation.py
transiflow/CrsMatrix.py
transiflow/CylindricalDiscretization.py
transiflow/Discretization.py
transiflow/TimeIntegration.py
transiflow/__init__.py
transiflow/plot_utils.py
transiflow/utils.py
transiflow/interface/BaseInterface.py
transiflow/interface/Epetra.py
transiflow/interface/HYMLS.py
transiflow/interface/JaDa.py
transiflow/interface/JaDaHYMLS.py
transiflow/interface/PETSc.py
transiflow/interface/ParallelBaseInterface.py
transiflow/interface/SciPy.py
transiflow/interface/__init__.py
transiflow/interface/create.py
transiflow-1.0.0.dist-info/LICENSE
transiflow-1.0.0.dist-info/METADATA
transiflow-1.0.0.dist-info/WHEEL
transiflow-1.0.0.dist-info/top_level.txt
transiflow-1.0.0.dist-info/RECORD
