Metadata-Version: 2.1
Name: transiflow
Version: 1.0.0
Summary: Implementations and continuation of some standard computational fluid dynamics problems using the finite volume method.
Home-page: https://github.com/BIMAU/transiflow
Author: Sven Baars
Author-email: s.baars@uu.nl
License: Apache License 2.0
Classifier: Development Status :: 5 - Production/Stable
Classifier: Environment :: Console
Classifier: Intended Audience :: Developers
Classifier: Intended Audience :: Science/Research
Classifier: License :: OSI Approved :: Apache Software License
Classifier: Operating System :: OS Independent
Classifier: Programming Language :: Python
Classifier: Topic :: Scientific/Engineering
License-File: LICENSE
Requires-Dist: numpy
Requires-Dist: scipy
Requires-Dist: matplotlib
Requires-Dist: jadapy
Provides-Extra: all
Requires-Dist: pytest; extra == "all"
Provides-Extra: test
Requires-Dist: pytest; extra == "test"
